palantyra/__init__.py
palantyra/api.py
palantyra/utils.py
Palantyra-1.0.6.dist-info/METADATA
Palantyra-1.0.6.dist-info/WHEEL
Palantyra-1.0.6.dist-info/top_level.txt
Palantyra-1.0.6.dist-info/RECORD
