Metadata-Version: 2.1
Name: Palantyra
Version: 1.0.6
Summary: AI observability platform for LLM applications - Python SDK
Home-page: https://github.com/tanmaysharma2001/palantyra-python-sdk
Author: Palantyra Team
Author-email: sharmatanmay617@gmail.com
Classifier: Development Status :: 4 - Beta
Classifier: Intended Audience :: Developers
Classifier: License :: OSI Approved :: MIT License
Classifier: Operating System :: OS Independent
Classifier: Programming Language :: Python :: 3
Classifier: Programming Language :: Python :: 3.8
Classifier: Programming Language :: Python :: 3.9
Classifier: Programming Language :: Python :: 3.10
Classifier: Programming Language :: Python :: 3.11
Classifier: Programming Language :: Python :: 3.12
Classifier: Topic :: Software Development :: Libraries :: Python Modules
Classifier: Topic :: System :: Monitoring
Classifier: Topic :: Scientific/Engineering :: Artificial Intelligence
Requires-Python: >=3.8
Requires-Dist: requests>=2.25.0
Requires-Dist: typing-extensions>=4.0.0
Requires-Dist: opentelemetry-api>=1.20.0
Requires-Dist: opentelemetry-sdk>=1.20.0
Requires-Dist: opentelemetry-exporter-otlp-proto-grpc>=1.20.0
Requires-Dist: opentelemetry-instrumentation>=0.41b0
Requires-Dist: opentelemetry-instrumentation-openai>=0.20.0
Provides-Extra: anthropic
Requires-Dist: anthropic>=0.3.0; extra == "anthropic"
Provides-Extra: async
Requires-Dist: httpx>=0.23.0; extra == "async"
Requires-Dist: aiohttp>=3.8.0; extra == "async"
Provides-Extra: dev
Requires-Dist: pytest>=7.0.0; extra == "dev"
Requires-Dist: pytest-asyncio>=0.21.0; extra == "dev"
Requires-Dist: black>=22.0.0; extra == "dev"
Requires-Dist: isort>=5.10.0; extra == "dev"
Requires-Dist: mypy>=1.0.0; extra == "dev"
Requires-Dist: pre-commit>=2.20.0; extra == "dev"
Provides-Extra: full
Requires-Dist: httpx>=0.23.0; extra == "full"
Requires-Dist: aiohttp>=3.8.0; extra == "full"
Requires-Dist: openai>=1.0.0; extra == "full"
Requires-Dist: anthropic>=0.3.0; extra == "full"
Provides-Extra: openai
Requires-Dist: openai>=1.0.0; extra == "openai"
